{
  "statistics": {
    "goalsScored": 35,
    "goalsConceded": 46,
    "ownGoals": 0,
    "assists": 22,
    "shots": 389,
    "penaltyGoals": 4,
    "penaltiesTaken": 4,
    "freeKickGoals": 1,
    "freeKickShots": 10,
    "goalsFromInsideTheBox": 31,
    "goalsFromOutsideTheBox": 3,
    "shotsFromInsideTheBox": 257,
    "shotsFromOutsideTheBox": 132,
    "headedGoals": 2,
    "leftFootGoals": 23,
    "rightFootGoals": 9,
    "bigChances": 76,
    "bigChancesCreated": 59,
    "bigChancesMissed": 55,
    "shotsOnTarget": 131,
    "shotsOffTarget": 155,
    "blockedScoringAttempt": 103,
    "successfulDribbles": 295,
    "dribbleAttempts": 602,
    "corners": 216,
    "hitWoodwork": 11,
    "fastBreaks": 34,
    "fastBreakGoals": 3,
    "fastBreakShots": 31,
    "averageBallPossession": 54.026315789474,
    "totalPasses": 16983,
    "accuratePasses": 13963,
    "accuratePassesPercentage": 82.217511629276,
    "totalOwnHalfPasses": 8221,
    "accurateOwnHalfPasses": 7385,
    "accurateOwnHalfPassesPercentage": 89.830920812553,
    "totalOppositionHalfPasses": 9502,
    "accurateOppositionHalfPasses": 6735,
    "accurateOppositionHalfPassesPercentage": 70.879814775837,
    "totalLongBalls": 1387,
    "accurateLongBalls": 658,
    "accurateLongBallsPercentage": 47.440519105984,
    "totalCrosses": 740,
    "accurateCrosses": 157,
    "accurateCrossesPercentage": 21.216216216216,
    "cleanSheets": 13,
    "tackles": 649,
    "interceptions": 283,
    "saves": 97,
    "errorsLeadingToGoal": 6,
    "errorsLeadingToShot": 15,
    "penaltiesCommited": 7,
    "penaltyGoalsConceded": 5,
    "clearances": 878,
    "clearancesOffLine": 2,
    "lastManTackles": 8,
    "totalDuels": 3899,
    "duelsWon": 1939,
    "duelsWonPercentage": 49.730700179533,
    "totalGroundDuels": 2686,
    "groundDuelsWon": 1354,
    "groundDuelsWonPercentage": 50.409530900968,
    "totalAerialDuels": 1213,
    "aerialDuelsWon": 585,
    "aerialDuelsWonPercentage": 48.227535037098,
    "possessionLost": 5144,
    "offsides": 82,
    "fouls": 501,
    "yellowCards": 85,
    "yellowRedCards": 0,
    "redCards": 4,
    "avgRating": 6.8339495798319,
    "accurateFinalThirdPassesAgainst": 3004,
    "accurateOppositionHalfPassesAgainst": 6059,
    "accurateOwnHalfPassesAgainst": 5805,
    "accuratePassesAgainst": 11707,
    "bigChancesAgainst": 70,
    "bigChancesCreatedAgainst": 46,
    "bigChancesMissedAgainst": 40,
    "clearancesAgainst": 941,
    "cornersAgainst": 179,
    "crossesSuccessfulAgainst": 157,
    "crossesTotalAgainst": 610,
    "dribbleAttemptsTotalAgainst": 579,
    "dribbleAttemptsWonAgainst": 271,
    "errorsLeadingToGoalAgainst": 4,
    "errorsLeadingToShotAgainst": 10,
    "hitWoodworkAgainst": 10,
    "interceptionsAgainst": 292,
    "keyPassesAgainst": 322,
    "longBallsSuccessfulAgainst": 937,
    "longBallsTotalAgainst": 2202,
    "offsidesAgainst": 85,
    "redCardsAgainst": 0,
    "shotsAgainst": 439,
    "shotsBlockedAgainst": 126,
    "shotsFromInsideTheBoxAgainst": 277,
    "shotsFromOutsideTheBoxAgainst": 162,
    "shotsOffTargetAgainst": 169,
    "shotsOnTargetAgainst": 144,
    "blockedScoringAttemptAgainst": 126,
    "tacklesAgainst": 604,
    "totalFinalThirdPassesAgainst": 4394,
    "oppositionHalfPassesTotalAgainst": 8736,
    "ownHalfPassesTotalAgainst": 6668,
    "totalPassesAgainst": 14794,
    "yellowCardsAgainst": 81,
    "throwIns": 832,
    "goalKicks": 271,
    "ballRecovery": 1777,
    "freeKicks": 417,
    "id": 24806,
    "matches": 38,
    "awardedMatches": 0,
    "statisticsType": {
      "sportSlug": "football",
      "statisticsType": "team"
    }
  }
}