{
  "statistics": {
    "goalsScored": 41,
    "goalsConceded": 56,
    "ownGoals": 5,
    "assists": 28,
    "shots": 434,
    "penaltyGoals": 2,
    "penaltiesTaken": 4,
    "freeKickGoals": 1,
    "freeKickShots": 15,
    "goalsFromInsideTheBox": 34,
    "goalsFromOutsideTheBox": 7,
    "shotsFromInsideTheBox": 270,
    "shotsFromOutsideTheBox": 164,
    "headedGoals": 9,
    "leftFootGoals": 10,
    "rightFootGoals": 21,
    "bigChances": 55,
    "bigChancesCreated": 38,
    "bigChancesMissed": 34,
    "shotsOnTarget": 143,
    "shotsOffTarget": 176,
    "blockedScoringAttempt": 115,
    "successfulDribbles": 281,
    "dribbleAttempts": 575,
    "corners": 178,
    "hitWoodwork": 13,
    "fastBreaks": 34,
    "fastBreakGoals": 5,
    "fastBreakShots": 31,
    "averageBallPossession": 47.236842105263,
    "totalPasses": 14759,
    "accuratePasses": 12098,
    "accuratePassesPercentage": 81.970323192628,
    "totalOwnHalfPasses": 7388,
    "accurateOwnHalfPasses": 6677,
    "accurateOwnHalfPassesPercentage": 90.376285868977,
    "totalOppositionHalfPasses": 8050,
    "accurateOppositionHalfPasses": 5591,
    "accurateOppositionHalfPassesPercentage": 69.453416149068,
    "totalLongBalls": 1467,
    "accurateLongBalls": 730,
    "accurateLongBallsPercentage": 49.761417859577,
    "totalCrosses": 679,
    "accurateCrosses": 170,
    "accurateCrossesPercentage": 25.036818851252,
    "cleanSheets": 9,
    "tackles": 562,
    "interceptions": 302,
    "saves": 114,
    "errorsLeadingToGoal": 6,
    "errorsLeadingToShot": 21,
    "penaltiesCommited": 8,
    "penaltyGoalsConceded": 7,
    "clearances": 853,
    "clearancesOffLine": 6,
    "lastManTackles": 4,
    "totalDuels": 3588,
    "duelsWon": 1772,
    "duelsWonPercentage": 49.386845039019,
    "totalGroundDuels": 2519,
    "groundDuelsWon": 1219,
    "groundDuelsWonPercentage": 48.392219134577,
    "totalAerialDuels": 1069,
    "aerialDuelsWon": 553,
    "aerialDuelsWonPercentage": 51.730589335828,
    "possessionLost": 4520,
    "offsides": 50,
    "fouls": 543,
    "yellowCards": 85,
    "yellowRedCards": 3,
    "redCards": 5,
    "avgRating": 6.8272572402044,
    "accurateFinalThirdPassesAgainst": 2762,
    "accurateOppositionHalfPassesAgainst": 5809,
    "accurateOwnHalfPassesAgainst": 8164,
    "accuratePassesAgainst": 13804,
    "bigChancesAgainst": 78,
    "bigChancesCreatedAgainst": 52,
    "bigChancesMissedAgainst": 46,
    "clearancesAgainst": 851,
    "cornersAgainst": 203,
    "crossesSuccessfulAgainst": 169,
    "crossesTotalAgainst": 677,
    "dribbleAttemptsTotalAgainst": 508,
    "dribbleAttemptsWonAgainst": 229,
    "errorsLeadingToGoalAgainst": 3,
    "errorsLeadingToShotAgainst": 12,
    "hitWoodworkAgainst": 11,
    "interceptionsAgainst": 270,
    "keyPassesAgainst": 365,
    "longBallsSuccessfulAgainst": 882,
    "longBallsTotalAgainst": 1912,
    "offsidesAgainst": 84,
    "redCardsAgainst": 5,
    "shotsAgainst": 504,
    "shotsBlockedAgainst": 145,
    "shotsFromInsideTheBoxAgainst": 355,
    "shotsFromOutsideTheBoxAgainst": 149,
    "shotsOffTargetAgainst": 189,
    "shotsOnTargetAgainst": 170,
    "blockedScoringAttemptAgainst": 145,
    "tacklesAgainst": 589,
    "totalFinalThirdPassesAgainst": 3947,
    "oppositionHalfPassesTotalAgainst": 8292,
    "ownHalfPassesTotalAgainst": 8938,
    "totalPassesAgainst": 16553,
    "yellowCardsAgainst": 57,
    "throwIns": 683,
    "goalKicks": 266,
    "ballRecovery": 1620,
    "freeKicks": 379,
    "id": 24799,
    "matches": 38,
    "awardedMatches": 0,
    "statisticsType": {
      "sportSlug": "football",
      "statisticsType": "team"
    }
  }
}