{
  "statistics": {
    "goalsScored": 54,
    "goalsConceded": 29,
    "ownGoals": 1,
    "assists": 40,
    "shots": 468,
    "penaltyGoals": 3,
    "penaltiesTaken": 6,
    "freeKickGoals": 0,
    "freeKickShots": 8,
    "goalsFromInsideTheBox": 47,
    "goalsFromOutsideTheBox": 6,
    "shotsFromInsideTheBox": 310,
    "shotsFromOutsideTheBox": 158,
    "headedGoals": 12,
    "leftFootGoals": 11,
    "rightFootGoals": 30,
    "bigChances": 84,
    "bigChancesCreated": 63,
    "bigChancesMissed": 53,
    "shotsOnTarget": 154,
    "shotsOffTarget": 199,
    "blockedScoringAttempt": 115,
    "successfulDribbles": 328,
    "dribbleAttempts": 716,
    "corners": 193,
    "hitWoodwork": 17,
    "fastBreaks": 33,
    "fastBreakGoals": 2,
    "fastBreakShots": 31,
    "averageBallPossession": 48.421052631579,
    "totalPasses": 15542,
    "accuratePasses": 12590,
    "accuratePassesPercentage": 81.006305494788,
    "totalOwnHalfPasses": 6778,
    "accurateOwnHalfPasses": 6062,
    "accurateOwnHalfPassesPercentage": 89.436411920921,
    "totalOppositionHalfPasses": 9536,
    "accurateOppositionHalfPasses": 6691,
    "accurateOppositionHalfPassesPercentage": 70.165687919463,
    "totalLongBalls": 1450,
    "accurateLongBalls": 706,
    "accurateLongBallsPercentage": 48.689655172414,
    "totalCrosses": 772,
    "accurateCrosses": 163,
    "accurateCrossesPercentage": 21.113989637306,
    "cleanSheets": 15,
    "tackles": 577,
    "interceptions": 344,
    "saves": 85,
    "errorsLeadingToGoal": 8,
    "errorsLeadingToShot": 17,
    "penaltiesCommited": 5,
    "penaltyGoalsConceded": 3,
    "clearances": 873,
    "clearancesOffLine": 1,
    "lastManTackles": 2,
    "totalDuels": 3835,
    "duelsWon": 1787,
    "duelsWonPercentage": 46.597131681877,
    "totalGroundDuels": 2806,
    "groundDuelsWon": 1281,
    "groundDuelsWonPercentage": 45.652173913043,
    "totalAerialDuels": 1029,
    "aerialDuelsWon": 506,
    "aerialDuelsWonPercentage": 49.173955296404,
    "possessionLost": 5154,
    "offsides": 68,
    "fouls": 483,
    "yellowCards": 63,
    "yellowRedCards": 1,
    "redCards": 3,
    "avgRating": 6.884,
    "accurateFinalThirdPassesAgainst": 2327,
    "accurateOppositionHalfPassesAgainst": 5478,
    "accurateOwnHalfPassesAgainst": 8620,
    "accuratePassesAgainst": 13963,
    "bigChancesAgainst": 64,
    "bigChancesCreatedAgainst": 44,
    "bigChancesMissedAgainst": 45,
    "clearancesAgainst": 893,
    "cornersAgainst": 155,
    "crossesSuccessfulAgainst": 135,
    "crossesTotalAgainst": 592,
    "dribbleAttemptsTotalAgainst": 579,
    "dribbleAttemptsWonAgainst": 283,
    "errorsLeadingToGoalAgainst": 8,
    "errorsLeadingToShotAgainst": 16,
    "hitWoodworkAgainst": 10,
    "interceptionsAgainst": 361,
    "keyPassesAgainst": 242,
    "longBallsSuccessfulAgainst": 929,
    "longBallsTotalAgainst": 2164,
    "offsidesAgainst": 84,
    "redCardsAgainst": 4,
    "shotsAgainst": 343,
    "shotsBlockedAgainst": 78,
    "shotsFromInsideTheBoxAgainst": 223,
    "shotsFromOutsideTheBoxAgainst": 120,
    "shotsOffTargetAgainst": 151,
    "shotsOnTargetAgainst": 114,
    "blockedScoringAttemptAgainst": 78,
    "tacklesAgainst": 789,
    "totalFinalThirdPassesAgainst": 3727,
    "oppositionHalfPassesTotalAgainst": 8255,
    "ownHalfPassesTotalAgainst": 9568,
    "totalPassesAgainst": 17231,
    "yellowCardsAgainst": 81,
    "throwIns": 836,
    "goalKicks": 229,
    "ballRecovery": 1989,
    "freeKicks": 386,
    "id": 24379,
    "matches": 38,
    "awardedMatches": 0,
    "statisticsType": {
      "sportSlug": "football",
      "statisticsType": "team"
    }
  }
}