{
  "statistics": {
    "goalsScored": 41,
    "goalsConceded": 45,
    "ownGoals": 3,
    "assists": 28,
    "shots": 427,
    "penaltyGoals": 2,
    "penaltiesTaken": 2,
    "freeKickGoals": 0,
    "freeKickShots": 12,
    "goalsFromInsideTheBox": 35,
    "goalsFromOutsideTheBox": 5,
    "shotsFromInsideTheBox": 258,
    "shotsFromOutsideTheBox": 169,
    "headedGoals": 8,
    "leftFootGoals": 6,
    "rightFootGoals": 26,
    "bigChances": 56,
    "bigChancesCreated": 45,
    "bigChancesMissed": 32,
    "shotsOnTarget": 137,
    "shotsOffTarget": 153,
    "blockedScoringAttempt": 137,
    "successfulDribbles": 251,
    "dribbleAttempts": 522,
    "corners": 183,
    "hitWoodwork": 6,
    "fastBreaks": 36,
    "fastBreakGoals": 4,
    "fastBreakShots": 32,
    "averageBallPossession": 47.088235294118,
    "totalPasses": 13897,
    "accuratePasses": 11424,
    "accuratePassesPercentage": 82.204792401238,
    "totalOwnHalfPasses": 6119,
    "accurateOwnHalfPasses": 5497,
    "accurateOwnHalfPassesPercentage": 89.83494034973,
    "totalOppositionHalfPasses": 7778,
    "accurateOppositionHalfPasses": 5927,
    "accurateOppositionHalfPassesPercentage": 76.202108511185,
    "totalLongBalls": 1181,
    "accurateLongBalls": 567,
    "accurateLongBallsPercentage": 48.01016088061,
    "totalCrosses": 774,
    "accurateCrosses": 160,
    "accurateCrossesPercentage": 20.671834625323,
    "cleanSheets": 9,
    "tackles": 570,
    "interceptions": 265,
    "saves": 92,
    "errorsLeadingToGoal": 8,
    "errorsLeadingToShot": 24,
    "penaltiesCommited": 5,
    "penaltyGoalsConceded": 5,
    "clearances": 876,
    "clearancesOffLine": 5,
    "lastManTackles": 7,
    "totalDuels": 3412,
    "duelsWon": 1696,
    "duelsWonPercentage": 49.706916764361,
    "totalGroundDuels": 2353,
    "groundDuelsWon": 1191,
    "groundDuelsWonPercentage": 50.616234594135,
    "totalAerialDuels": 1059,
    "aerialDuelsWon": 505,
    "aerialDuelsWonPercentage": 47.686496694995,
    "possessionLost": 4463,
    "offsides": 54,
    "fouls": 365,
    "yellowCards": 55,
    "yellowRedCards": 0,
    "redCards": 1,
    "avgRating": 6.8030425963489,
    "accurateFinalThirdPassesAgainst": 3217,
    "accurateOppositionHalfPassesAgainst": 6300,
    "accurateOwnHalfPassesAgainst": 6835,
    "accuratePassesAgainst": 13135,
    "bigChancesAgainst": 80,
    "bigChancesCreatedAgainst": 58,
    "bigChancesMissedAgainst": 54,
    "clearancesAgainst": 872,
    "cornersAgainst": 162,
    "crossesSuccessfulAgainst": 149,
    "crossesTotalAgainst": 615,
    "dribbleAttemptsTotalAgainst": 542,
    "dribbleAttemptsWonAgainst": 257,
    "errorsLeadingToGoalAgainst": 5,
    "errorsLeadingToShotAgainst": 18,
    "hitWoodworkAgainst": 12,
    "interceptionsAgainst": 287,
    "keyPassesAgainst": 323,
    "longBallsSuccessfulAgainst": 708,
    "longBallsTotalAgainst": 1691,
    "offsidesAgainst": 33,
    "redCardsAgainst": 1,
    "shotsAgainst": 423,
    "shotsBlockedAgainst": 136,
    "shotsFromInsideTheBoxAgainst": 288,
    "shotsFromOutsideTheBoxAgainst": 135,
    "shotsOffTargetAgainst": 149,
    "shotsOnTargetAgainst": 140,
    "blockedScoringAttemptAgainst": 134,
    "tacklesAgainst": 567,
    "totalFinalThirdPassesAgainst": 4472,
    "oppositionHalfPassesTotalAgainst": 8284,
    "ownHalfPassesTotalAgainst": 7474,
    "totalPassesAgainst": 15758,
    "yellowCardsAgainst": 61,
    "throwIns": 624,
    "goalKicks": 263,
    "ballRecovery": 1611,
    "freeKicks": 383,
    "id": 48369,
    "matches": 34,
    "awardedMatches": 0,
    "statisticsType": {
      "sportSlug": "football",
      "statisticsType": "team"
    }
  }
}