{
  "statistics": {
    "goalsScored": 48,
    "goalsConceded": 27,
    "ownGoals": 1,
    "assists": 34,
    "shots": 452,
    "penaltyGoals": 5,
    "penaltiesTaken": 7,
    "freeKickGoals": 0,
    "freeKickShots": 8,
    "goalsFromInsideTheBox": 39,
    "goalsFromOutsideTheBox": 9,
    "shotsFromInsideTheBox": 318,
    "shotsFromOutsideTheBox": 134,
    "headedGoals": 6,
    "leftFootGoals": 19,
    "rightFootGoals": 22,
    "bigChances": 91,
    "bigChancesCreated": 67,
    "bigChancesMissed": 60,
    "shotsOnTarget": 147,
    "shotsOffTarget": 185,
    "blockedScoringAttempt": 120,
    "successfulDribbles": 220,
    "dribbleAttempts": 489,
    "corners": 148,
    "hitWoodwork": 15,
    "fastBreaks": 39,
    "fastBreakGoals": 6,
    "fastBreakShots": 34,
    "averageBallPossession": 52.470588235294,
    "totalPasses": 16705,
    "accuratePasses": 14616,
    "accuratePassesPercentage": 87.494762047291,
    "totalOwnHalfPasses": 7880,
    "accurateOwnHalfPasses": 7329,
    "accurateOwnHalfPassesPercentage": 93.007614213198,
    "totalOppositionHalfPasses": 8825,
    "accurateOppositionHalfPasses": 7287,
    "accurateOppositionHalfPassesPercentage": 82.57223796034,
    "totalLongBalls": 1046,
    "accurateLongBalls": 605,
    "accurateLongBallsPercentage": 57.839388145315,
    "totalCrosses": 580,
    "accurateCrosses": 170,
    "accurateCrossesPercentage": 29.310344827586,
    "cleanSheets": 15,
    "tackles": 495,
    "interceptions": 225,
    "saves": 98,
    "errorsLeadingToGoal": 1,
    "errorsLeadingToShot": 27,
    "penaltiesCommited": 8,
    "penaltyGoalsConceded": 5,
    "clearances": 749,
    "clearancesOffLine": 0,
    "lastManTackles": 2,
    "totalDuels": 2822,
    "duelsWon": 1478,
    "duelsWonPercentage": 52.374202693125,
    "totalGroundDuels": 2064,
    "groundDuelsWon": 1087,
    "groundDuelsWonPercentage": 52.664728682171,
    "totalAerialDuels": 758,
    "aerialDuelsWon": 391,
    "aerialDuelsWonPercentage": 51.583113456464,
    "possessionLost": 3633,
    "offsides": 64,
    "fouls": 333,
    "yellowCards": 51,
    "yellowRedCards": 1,
    "redCards": 2,
    "avgRating": 6.9451485148515,
    "accurateFinalThirdPassesAgainst": 3177,
    "accurateOppositionHalfPassesAgainst": 6740,
    "accurateOwnHalfPassesAgainst": 6242,
    "accuratePassesAgainst": 12982,
    "bigChancesAgainst": 52,
    "bigChancesCreatedAgainst": 36,
    "bigChancesMissedAgainst": 31,
    "clearancesAgainst": 735,
    "cornersAgainst": 150,
    "crossesSuccessfulAgainst": 169,
    "crossesTotalAgainst": 702,
    "dribbleAttemptsTotalAgainst": 428,
    "dribbleAttemptsWonAgainst": 191,
    "errorsLeadingToGoalAgainst": 4,
    "errorsLeadingToShotAgainst": 20,
    "hitWoodworkAgainst": 13,
    "interceptionsAgainst": 275,
    "keyPassesAgainst": 295,
    "longBallsSuccessfulAgainst": 736,
    "longBallsTotalAgainst": 1465,
    "offsidesAgainst": 40,
    "redCardsAgainst": 0,
    "shotsAgainst": 380,
    "shotsBlockedAgainst": 106,
    "shotsFromInsideTheBoxAgainst": 229,
    "shotsFromOutsideTheBoxAgainst": 151,
    "shotsOffTargetAgainst": 155,
    "shotsOnTargetAgainst": 119,
    "blockedScoringAttemptAgainst": 106,
    "tacklesAgainst": 485,
    "totalFinalThirdPassesAgainst": 4096,
    "oppositionHalfPassesTotalAgainst": 8200,
    "ownHalfPassesTotalAgainst": 6770,
    "totalPassesAgainst": 14970,
    "yellowCardsAgainst": 68,
    "throwIns": 596,
    "goalKicks": 230,
    "ballRecovery": 1476,
    "freeKicks": 378,
    "id": 49109,
    "matches": 34,
    "awardedMatches": 0,
    "statisticsType": {
      "sportSlug": "football",
      "statisticsType": "team"
    }
  }
}