{
  "statistics": {
    "goalsScored": 42,
    "goalsConceded": 55,
    "ownGoals": 1,
    "assists": 32,
    "shots": 475,
    "penaltyGoals": 2,
    "penaltiesTaken": 3,
    "freeKickGoals": 0,
    "freeKickShots": 14,
    "goalsFromInsideTheBox": 32,
    "goalsFromOutsideTheBox": 7,
    "shotsFromInsideTheBox": 282,
    "shotsFromOutsideTheBox": 192,
    "headedGoals": 5,
    "leftFootGoals": 17,
    "rightFootGoals": 17,
    "bigChances": 70,
    "bigChancesCreated": 53,
    "bigChancesMissed": 49,
    "shotsOnTarget": 156,
    "shotsOffTarget": 206,
    "blockedScoringAttempt": 113,
    "successfulDribbles": 339,
    "dribbleAttempts": 659,
    "corners": 185,
    "hitWoodwork": 13,
    "fastBreaks": 44,
    "fastBreakGoals": 4,
    "fastBreakShots": 40,
    "averageBallPossession": 50.605263157895,
    "totalPasses": 16451,
    "accuratePasses": 13510,
    "accuratePassesPercentage": 82.122667315057,
    "totalOwnHalfPasses": 8617,
    "accurateOwnHalfPasses": 7791,
    "accurateOwnHalfPassesPercentage": 90.414297319253,
    "totalOppositionHalfPasses": 8446,
    "accurateOppositionHalfPasses": 5851,
    "accurateOppositionHalfPassesPercentage": 69.275396637462,
    "totalLongBalls": 1377,
    "accurateLongBalls": 619,
    "accurateLongBallsPercentage": 44.952795933188,
    "totalCrosses": 612,
    "accurateCrosses": 132,
    "accurateCrossesPercentage": 21.56862745098,
    "cleanSheets": 10,
    "tackles": 648,
    "interceptions": 367,
    "saves": 94,
    "errorsLeadingToGoal": 3,
    "errorsLeadingToShot": 14,
    "penaltiesCommited": 6,
    "penaltyGoalsConceded": 5,
    "clearances": 883,
    "clearancesOffLine": 2,
    "lastManTackles": 9,
    "totalDuels": 3733,
    "duelsWon": 1920,
    "duelsWonPercentage": 51.433163675328,
    "totalGroundDuels": 2734,
    "groundDuelsWon": 1374,
    "groundDuelsWonPercentage": 50.256035113387,
    "totalAerialDuels": 999,
    "aerialDuelsWon": 546,
    "aerialDuelsWonPercentage": 54.654654654655,
    "possessionLost": 4955,
    "offsides": 70,
    "fouls": 494,
    "yellowCards": 95,
    "yellowRedCards": 3,
    "redCards": 8,
    "avgRating": 6.8212173913043,
    "accurateFinalThirdPassesAgainst": 2944,
    "accurateOppositionHalfPassesAgainst": 6538,
    "accurateOwnHalfPassesAgainst": 6929,
    "accuratePassesAgainst": 13322,
    "bigChancesAgainst": 81,
    "bigChancesCreatedAgainst": 58,
    "bigChancesMissedAgainst": 53,
    "clearancesAgainst": 860,
    "cornersAgainst": 165,
    "crossesSuccessfulAgainst": 145,
    "crossesTotalAgainst": 661,
    "dribbleAttemptsTotalAgainst": 563,
    "dribbleAttemptsWonAgainst": 251,
    "errorsLeadingToGoalAgainst": 3,
    "errorsLeadingToShotAgainst": 19,
    "hitWoodworkAgainst": 14,
    "interceptionsAgainst": 283,
    "keyPassesAgainst": 308,
    "longBallsSuccessfulAgainst": 884,
    "longBallsTotalAgainst": 1990,
    "offsidesAgainst": 62,
    "redCardsAgainst": 4,
    "shotsAgainst": 415,
    "shotsBlockedAgainst": 88,
    "shotsFromInsideTheBoxAgainst": 267,
    "shotsFromOutsideTheBoxAgainst": 148,
    "shotsOffTargetAgainst": 177,
    "shotsOnTargetAgainst": 150,
    "blockedScoringAttemptAgainst": 88,
    "tacklesAgainst": 651,
    "totalFinalThirdPassesAgainst": 4392,
    "oppositionHalfPassesTotalAgainst": 9315,
    "ownHalfPassesTotalAgainst": 7642,
    "totalPassesAgainst": 16296,
    "yellowCardsAgainst": 94,
    "throwIns": 778,
    "goalKicks": 264,
    "ballRecovery": 1789,
    "freeKicks": 402,
    "id": 24554,
    "matches": 38,
    "awardedMatches": 0,
    "statisticsType": {
      "sportSlug": "football",
      "statisticsType": "team"
    }
  }
}