{
  "player": {
    "name": "Manuel Ugarte",
    "firstName": "Manuel",
    "lastName": "Ugarte",
    "slug": "manuel-ugarte",
    "shortName": "M. Ugarte",
    "team": {
      "name": "Manchester United",
      "slug": "manchester-united",
      "shortName": "Man Utd",
      "gender": "M",
      "sport": {
        "name": "Football",
        "slug": "football",
        "id": 1
      },
      "tournament": {
        "name": "Premier League",
        "slug": "premier-league",
        "category": {
          "name": "England",
          "slug": "england",
          "sport": {
            "name": "Football",
            "slug": "football",
            "id": 1
          },
          "priority": 10,
          "country": {
            "alpha2": "EN",
            "alpha3": "ENG",
            "name": "England",
            "slug": "england"
          },
          "id": 1,
          "flag": "england",
          "alpha2": "EN",
          "fieldTranslations": {
            "nameTranslation": {
              "ar": "إنجلترا",
              "hi": "इंग्लैंड",
              "bn": "ইংল্যান্ড",
              "ru": "Англия"
            },
            "shortNameTranslation": {}
          }
        },
        "uniqueTournament": {
          "name": "Premier League",
          "slug": "premier-league",
          "primaryColorHex": "#3c1c5a",
          "secondaryColorHex": "#f80158",
          "category": {
            "name": "England",
            "slug": "england",
            "sport": {
              "name": "Football",
              "slug": "football",
              "id": 1
            },
            "priority": 10,
            "country": {
              "alpha2": "EN",
              "alpha3": "ENG",
              "name": "England",
              "slug": "england"
            },
            "id": 1,
            "flag": "england",
            "alpha2": "EN",
            "fieldTranslations": {
              "nameTranslation": {
                "ar": "إنجلترا",
                "hi": "इंग्लैंड",
                "bn": "ইংল্যান্ড",
                "ru": "Англия"
              },
              "shortNameTranslation": {}
            }
          },
          "userCount": 1201112,
          "country": {},
          "id": 17,
          "displayInverseHomeAwayTeams": false,
          "fieldTranslations": {
            "nameTranslation": {
              "ar": "الدوري الإنجليزي الممتاز",
              "hi": "प्रिमियर लीग",
              "bn": "প্রিমিয়ার লীগ"
            },
            "shortNameTranslation": {}
          }
        },
        "priority": 701,
        "isLive": false,
        "id": 1,
        "fieldTranslations": {
          "nameTranslation": {
            "hi": "प्रिमियर लीग",
            "ar": "الدوري الإنجليزي الممتاز",
            "bn": "প্রিমিয়ার লীগ"
          },
          "shortNameTranslation": {}
        }
      },
      "primaryUniqueTournament": {
        "name": "Premier League",
        "slug": "premier-league",
        "primaryColorHex": "#3c1c5a",
        "secondaryColorHex": "#f80158",
        "category": {
          "name": "England",
          "slug": "england",
          "sport": {
            "name": "Football",
            "slug": "football",
            "id": 1
          },
          "priority": 10,
          "country": {
            "alpha2": "EN",
            "alpha3": "ENG",
            "name": "England",
            "slug": "england"
          },
          "id": 1,
          "flag": "england",
          "alpha2": "EN",
          "fieldTranslations": {
            "nameTranslation": {
              "ar": "إنجلترا",
              "hi": "इंग्लैंड",
              "bn": "ইংল্যান্ড",
              "ru": "Англия"
            },
            "shortNameTranslation": {}
          }
        },
        "userCount": 1201112,
        "country": {},
        "id": 17,
        "displayInverseHomeAwayTeams": false,
        "fieldTranslations": {
          "nameTranslation": {
            "ar": "الدوري الإنجليزي الممتاز",
            "hi": "प्रिमियर लीग",
            "bn": "প্রিমিয়ার লীগ"
          },
          "shortNameTranslation": {}
        }
      },
      "userCount": 3517935,
      "nameCode": "MUN",
      "disabled": false,
      "national": false,
      "type": 0,
      "country": {
        "alpha2": "EN",
        "alpha3": "ENG",
        "name": "England",
        "slug": "england"
      },
      "id": 35,
      "teamColors": {
        "primary": "#ff0000",
        "secondary": "#373737",
        "text": "#373737"
      },
      "fieldTranslations": {
        "nameTranslation": {
          "ar": "مانتشستر يونايتد",
          "hi": "मेनचेस्टर यूनाइटेड ऍफ़सी",
          "ru": "Манчестер Юнайтед"
        },
        "shortNameTranslation": {
          "ar": "مان يونايتد",
          "bn": "ম্যান ইউনাইটেড",
          "hi": "मैन यूनाइटेड"
        }
      }
    },
    "position": "M",
    "positionsDetailed": [
      "MC",
      "DM"
    ],
    "jerseyNumber": "25",
    "height": 182,
    "dateOfBirth": "2001-04-11T00:00:00+00:00",
    "preferredFoot": "Right",
    "userCount": 19931,
    "gender": "M",
    "sofascoreId": "ugartemanu",
    "country": {
      "alpha2": "UY",
      "alpha3": "URY",
      "name": "Uruguay",
      "slug": "uruguay"
    },
    "id": 846425,
    "shirtNumber": 25,
    "dateOfBirthTimestamp": 986947200,
    "contractUntilTimestamp": 1877472000,
    "proposedMarketValue": 29000000,
    "proposedMarketValueRaw": {
      "value": 29000000,
      "currency": "EUR"
    },
    "fieldTranslations": {
      "nameTranslation": {
        "ar": "مانويل أوغارتي",
        "bn": "ম্যানুয়েল উগার্তে",
        "hi": "मैनुअल उगार्टे"
      },
      "shortNameTranslation": {
        "ar": "م. أوغارتي",
        "bn": "এম. উগার্তে",
        "hi": "एम. उगार्टे"
      }
    }
  }
}