{
  "player": {
    "name": "Giovani Lo Celso",
    "slug": "lo-celso-giovani",
    "shortName": "G. Lo Celso",
    "team": {
      "name": "Real Betis",
      "slug": "real-betis",
      "shortName": "Real Betis",
      "gender": "M",
      "sport": {
        "name": "Football",
        "slug": "football",
        "id": 1
      },
      "tournament": {
        "name": "LaLiga",
        "slug": "laliga",
        "category": {
          "name": "Spain",
          "slug": "spain",
          "sport": {
            "name": "Football",
            "slug": "football",
            "id": 1
          },
          "priority": 9,
          "country": {
            "alpha2": "ES",
            "alpha3": "ESP",
            "name": "Spain",
            "slug": "spain"
          },
          "id": 32,
          "flag": "spain",
          "alpha2": "ES",
          "fieldTranslations": {
            "nameTranslation": {
              "hi": "स्पेन",
              "ar": "إسبانيا",
              "bn": "স্পেন",
              "ru": "Испания"
            },
            "shortNameTranslation": {}
          }
        },
        "uniqueTournament": {
          "name": "LaLiga",
          "slug": "laliga",
          "primaryColorHex": "#2f4a89",
          "secondaryColorHex": "#f4a32e",
          "category": {
            "name": "Spain",
            "slug": "spain",
            "sport": {
              "name": "Football",
              "slug": "football",
              "id": 1
            },
            "priority": 9,
            "country": {
              "alpha2": "ES",
              "alpha3": "ESP",
              "name": "Spain",
              "slug": "spain"
            },
            "id": 32,
            "flag": "spain",
            "alpha2": "ES",
            "fieldTranslations": {
              "nameTranslation": {
                "hi": "स्पेन",
                "ar": "إسبانيا",
                "bn": "স্পেন",
                "ru": "Испания"
              },
              "shortNameTranslation": {}
            }
          },
          "userCount": 844000,
          "country": {},
          "id": 8,
          "displayInverseHomeAwayTeams": false,
          "fieldTranslations": {
            "nameTranslation": {
              "ar": "الدوري الإسباني",
              "hi": "ला लिगा",
              "bn": "লা লীগা"
            },
            "shortNameTranslation": {}
          }
        },
        "priority": 699,
        "isLive": false,
        "id": 36,
        "fieldTranslations": {
          "nameTranslation": {
            "hi": "ला लीगा",
            "ar": "الدوري الإسباني",
            "bn": "লা লীগা"
          },
          "shortNameTranslation": {}
        }
      },
      "primaryUniqueTournament": {
        "name": "LaLiga",
        "slug": "laliga",
        "primaryColorHex": "#2f4a89",
        "secondaryColorHex": "#f4a32e",
        "category": {
          "name": "Spain",
          "slug": "spain",
          "sport": {
            "name": "Football",
            "slug": "football",
            "id": 1
          },
          "priority": 9,
          "country": {
            "alpha2": "ES",
            "alpha3": "ESP",
            "name": "Spain",
            "slug": "spain"
          },
          "id": 32,
          "flag": "spain",
          "alpha2": "ES",
          "fieldTranslations": {
            "nameTranslation": {
              "hi": "स्पेन",
              "ar": "إسبانيا",
              "bn": "স্পেন",
              "ru": "Испания"
            },
            "shortNameTranslation": {}
          }
        },
        "userCount": 844000,
        "country": {},
        "id": 8,
        "displayInverseHomeAwayTeams": false,
        "fieldTranslations": {
          "nameTranslation": {
            "ar": "الدوري الإسباني",
            "hi": "ला लिगा",
            "bn": "লা লীগা"
          },
          "shortNameTranslation": {}
        }
      },
      "userCount": 589018,
      "nameCode": "BET",
      "disabled": false,
      "national": false,
      "type": 0,
      "country": {
        "alpha2": "ES",
        "alpha3": "ESP",
        "name": "Spain",
        "slug": "spain"
      },
      "id": 2816,
      "teamColors": {
        "primary": "#ffffff",
        "secondary": "#006633",
        "text": "#006633"
      },
      "fieldTranslations": {
        "nameTranslation": {
          "ar": "ريال بيتيس",
          "ru": "Реал Бетис"
        },
        "shortNameTranslation": {
          "ar": "ريال بيتيس",
          "bn": "বেটিস",
          "hi": "बेटिस"
        }
      }
    },
    "position": "M",
    "positionsDetailed": [
      "AM",
      "MC"
    ],
    "weight": 70,
    "jerseyNumber": "20",
    "height": 177,
    "dateOfBirth": "1996-04-09T00:00:00+00:00",
    "preferredFoot": "Left",
    "userCount": 15949,
    "deceased": false,
    "gender": "M",
    "sofascoreId": "locelso_giovani",
    "country": {
      "alpha2": "AR",
      "alpha3": "ARG",
      "name": "Argentina",
      "slug": "argentina"
    },
    "id": 798835,
    "shirtNumber": 20,
    "dateOfBirthTimestamp": 829008000,
    "contractUntilTimestamp": 1845936000,
    "proposedMarketValue": 14600000,
    "proposedMarketValueRaw": {
      "value": 14600000,
      "currency": "EUR"
    },
    "fieldTranslations": {
      "nameTranslation": {
        "ar": "جيوفاني لو سيلسو",
        "bn": "লো সেলসো, জিওভানি",
        "hi": "लो सेल्सो, जियोवानी"
      },
      "shortNameTranslation": {
        "ar": "ج. لو سيلسو",
        "bn": "জি. লো সেলসো",
        "hi": "जी. सेल्सो,"
      }
    }
  }
}